{
  "generated_at": "2026-05-23T03:41:13.425887+08:00",
  "total_titles_processed": 404,
  "failed_sources": [],
  "trends": [
    {
      "keyword_group": "谷歌 google gemini",
      "match_count": 1,
      "titles": [
        {
          "title": "苹果谷歌英伟达，集体松了口气",
          "url": "https://news.ifeng.com/c/8tL3ZUXTPWj",
          "source": "凤凰网",
          "ranks": [
            9
          ],
          "is_new": false,
          "appearance_count": 4,
          "time_info": "[01时06分 ~ 03时41分]"
        }
      ]
    },
    {
      "keyword_group": "東京大学 化学専攻 教授",
      "match_count": 1,
      "titles": [
        {
          "title": "《最强大脑》的魏坤琳教授已经48岁了",
          "url": "https://www.toutiao.com/trending/7642485722229981247/",
          "source": "今日头条",
          "ranks": [
            12,
            13
          ],
          "is_new": false,
          "appearance_count": 4,
          "time_info": "[01时06分 ~ 03时41分]"
        }
      ]
    }
  ],
  "report_image_url": "https://joyce677.github.io/TrendRadar/img/news.jpg"
}